README.md
setup.py
staintools/__init__.py
staintools/reinhard_color_normalizer.py
staintools/stain_augmentor.py
staintools/stain_normalizer.py
staintools.egg-info/PKG-INFO
staintools.egg-info/SOURCES.txt
staintools.egg-info/dependency_links.txt
staintools.egg-info/requires.txt
staintools.egg-info/top_level.txt
staintools/miscellaneous/__init__.py
staintools/miscellaneous/exceptions.py
staintools/miscellaneous/get_concentrations.py
staintools/miscellaneous/miscellaneous_functions.py
staintools/miscellaneous/optical_density_conversion.py
staintools/preprocessing/__init__.py
staintools/preprocessing/input_validation.py
staintools/preprocessing/luminosity_standardizer.py
staintools/preprocessing/read_image.py
staintools/stain_extraction/__init__.py
staintools/stain_extraction/abc_stain_extractor.py
staintools/stain_extraction/macenko_stain_extractor.py
staintools/stain_extraction/vahadane_stain_extractor.py
staintools/tissue_masks/__init__.py
staintools/tissue_masks/abc_tissue_locator.py
staintools/tissue_masks/luminosity_threshold_tissue_locator.py
staintools/visualization/__init__.py
staintools/visualization/visualization.py
tests/__init__.py
tests/test_miscellaneous.py