Metadata-Version: 1.0
Name: staintools
Version: 2.1.2
Summary: A package for tissue image stain normalization, augmentation and more.
Home-page: https://github.com/Peter554/StainTools
Author: Peter Byfield
Author-email: byfield554@gmail.com
License: UNKNOWN
Platform: UNKNOWN
